Proyecto2/src/design/B1_lector_teclado.sv
module B1_lector_teclado #(
    parameter int MAX_COUNT = 100000
)(
    input  logic       clk,
    input  logic [3:0] rows,

    output logic [2:0] cols,
    output logic [3:0] tecla,
    output logic       tecla_raw
);

    // ================================
    // Registros internos
    // ================================
    logic [24:0] contador = '0;
    logic [1:0]  estado   = '0;

    // ================================
    // SCAN DE COLUMNAS
    // ================================
    always_ff @(posedge clk) begin

        // congelar scanner mientras haya tecla
        if (!tecla_raw) begin

            contador <= contador + 1'b1;

            if (contador >= MAX_COUNT) begin

                contador <= '0;

                if (estado == 2)
                    estado <= 0;
                else
                    estado <= estado + 1'b1;

            end

        end
        else begin

            // opcional pero recomendado
            contador <= '0;

        end

    end

    // ================================
    // LECTURA DEL TECLADO
    // ================================
    always_comb begin

        cols      = 3'b000;
        tecla     = 4'h0;
        tecla_raw = 1'b0;

        case (estado)

            // =========================
            // COLUMNA 1
            // =========================
            0: begin

                cols = 3'b001;

                if (rows[0]) begin
                    tecla     = 4'h1;
                    tecla_raw = 1'b1;
                end
                else if (rows[1]) begin
                    tecla     = 4'h4;
                    tecla_raw = 1'b1;
                end
                else if (rows[2]) begin
                    tecla     = 4'h7;
                    tecla_raw = 1'b1;
                end
                else if (rows[3]) begin
                    tecla     = 4'hA;
                    tecla_raw = 1'b1;
                end

            end

            // =========================
            // COLUMNA 2
            // =========================
            1: begin

                cols = 3'b010;

                if (rows[0]) begin
                    tecla     = 4'h2;
                    tecla_raw = 1'b1;
                end
                else if (rows[1]) begin
                    tecla     = 4'h5;
                    tecla_raw = 1'b1;
                end
                else if (rows[2]) begin
                    tecla     = 4'h8;
                    tecla_raw = 1'b1;
                end
                else if (rows[3]) begin
                    tecla     = 4'h0;
                    tecla_raw = 1'b1;
                end

            end

            // =========================
            // COLUMNA 3
            // =========================
            2: begin

                cols = 3'b100;

                if (rows[0]) begin
                    tecla     = 4'h3;
                    tecla_raw = 1'b1;
                end
                else if (rows[1]) begin
                    tecla     = 4'h6;
                    tecla_raw = 1'b1;
                end
                else if (rows[2]) begin
                    tecla     = 4'h9;
                    tecla_raw = 1'b1;
                end
                else if (rows[3]) begin
                    tecla     = 4'hB;
                    tecla_raw = 1'b1;
                end

            end

            default: begin
                cols      = 3'b000;
                tecla     = 4'h0;
                tecla_raw = 1'b0;
            end

        endcase

    end

endmodule

Proyecto2/src/sim/B1_lector_teclado_tb.sv
`timescale 1ns/1ps

module B1_lector_teclado_tb;

    // ==========================
    // Señales
    // ==========================
    logic clk;
    logic [3:0] rows;

    logic [2:0] cols;
    logic [3:0] tecla;
    logic       tecla_raw;

    // ==========================
    // DUT
    // ==========================
    B1_lector_teclado #(
        .MAX_COUNT(5)
    ) dut (
        .clk(clk),
        .rows(rows),
        .cols(cols),
        .tecla(tecla),
        .tecla_raw(tecla_raw)
    );

    // ==========================
    // CLOCK
    // ==========================
    initial begin
        clk = 0;
        forever #5 clk = ~clk;
    end

    // ==========================
    // VCD
    // ==========================
    initial begin
        $dumpfile("B1_lector_teclado_tb.vcd");
        $dumpvars(0, B1_lector_teclado_tb);
    end

    // ==========================
    // ESTÍMULOS
    // ==========================
    initial begin

        rows = 4'b0000;

        // esperar scans
        #100;

        // tecla "1"
        rows = 4'b0001;
        #100;

        // soltar
        rows = 4'b0000;
        #100;

        // tecla "5"
        rows = 4'b0010;
        #100;

        // tecla "9"
        rows = 4'b0100;
        #100;

        // tecla "B"
        rows = 4'b1000;
        #100;

        $finish;

    end

endmodule

Proyecto2/src/build/B1_lector_teclado_tb.vcd
$date
	Thu May 14 01:16:45 2026
$end
$version
	Icarus Verilog
$end
$timescale
	1ps
$end
$scope module B1_lector_teclado_tb $end
$var wire 1 ! tecla_raw $end
$var wire 4 " tecla [3:0] $end
$var wire 3 # cols [2:0] $end
$var reg 1 $ clk $end
$var reg 4 % rows [3:0] $end
$scope module dut $end
$var wire 1 $ clk $end
$var wire 4 & rows [3:0] $end
$var parameter 32 ' MAX_COUNT $end
$var reg 3 ( cols [2:0] $end
$var reg 25 ) contador [24:0] $end
$var reg 2 * estado [1:0] $end
$var reg 4 + tecla [3:0] $end
$var reg 1 ! tecla_raw $end
$upscope $end
$upscope $end
$enddefinitions $end
$comment Show the parameter values. $end
$dumpall
b101 '
$end
#0
$dumpvars
b0 +
b0 *
b0 )
b1 (
b0 &
b0 %
0$
b1 #
b0 "
0!
$end
#5000
b1 )
1$
#10000
0$
#15000
b10 )
1$
#20000
0$
#25000
b11 )
1$
#30000
0$
#35000
b100 )
1$
#40000
0$
#45000
b101 )
1$
#50000
0$
#55000
b10 #
b10 (
b1 *
b0 )
1$
#60000
0$
#65000
b1 )
1$
#70000
0$
#75000
b10 )
1$
#80000
0$
#85000
b11 )
1$
#90000
0$
#95000
b100 )
1$
#100000
1!
b10 "
b10 +
b10 #
b10 (
0$
b1 %
b1 &
#105000
b101 )
1$
#110000
0$
#115000
b0 )
1$
#120000
0$
#125000
b1 )
1$
#130000
0$
#135000
b10 )
1$
#140000
0$
#145000
b11 )
1$
#150000
0$
#155000
b100 )
1$
#160000
0$
#165000
b101 )
1$
#170000
0$
#175000
b0 )
1$
#180000
0$
#185000
b1 )
1$
#190000
0$
#195000
b10 )
1$
#200000
0!
b0 "
b0 +
b10 #
b10 (
0$
b0 %
b0 &
#205000
b11 )
1$
#210000
0$
#215000
b100 )
1$
#220000
0$
#225000
b101 )
1$
#230000
0$
#235000
b100 #
b100 (
b10 *
b0 )
1$
#240000
0$
#245000
b1 )
1$
#250000
0$
#255000
b10 )
1$
#260000
0$
#265000
b11 )
1$
#270000
0$
#275000
b100 )
1$
#280000
0$
#285000
b101 )
1$
#290000
0$
#295000
b1 #
b1 (
b0 *
b0 )
1$
#300000
1!
b100 "
b100 +
b1 #
b1 (
0$
b10 %
b10 &
#305000
b1 )
1$
#310000
0$
#315000
b10 )
1$
#320000
0$
#325000
b11 )
1$
#330000
0$
#335000
b100 )
1$
#340000
0$
#345000
b101 )
1$
#350000
0$
#355000
b0 )
1$
#360000
0$
#365000
b1 )
1$
#370000
0$
#375000
b10 )
1$
#380000
0$
#385000
b11 )
1$
#390000
0$
#395000
b100 )
1$
#400000
1!
b111 "
b111 +
b1 #
b1 (
0$
b100 %
b100 &
#405000
b101 )
1$
#410000
0$
#415000
b0 )
1$
#420000
0$
#425000
b1 )
1$
#430000
0$
#435000
b10 )
1$
#440000
0$
#445000
b11 )
1$
#450000
0$
#455000
b100 )
1$
#460000
0$
#465000
b101 )
1$
#470000
0$
#475000
b0 )
1$
#480000
0$
#485000
b1 )
1$
#490000
0$
#495000
b10 )
1$
#500000
1!
b1010 "
b1010 +
b1 #
b1 (
0$
b1000 %
b1000 &
#505000
b11 )
1$
#510000
0$
#515000
b100 )
1$
#520000
0$
#525000
b101 )
1$
#530000
0$
#535000
b0 )
1$
#540000
0$
#545000
b1 )
1$
#550000
0$
#555000
b10 )
1$
#560000
0$
#565000
b11 )
1$
#570000
0$
#575000
b100 )
1$
#580000
0$
#585000
b101 )
1$
#590000
0$
#595000
b0 )
1$
