Proyecto2/src/design/B2_antreb.sv
module B2_antreb #(
    parameter NUM_CYCLES = 13
)
(
    input logic clk,
    input logic btn,
    output logic cs_antreb
);

logic ff_a;
logic ff_b;
logic ff_c;

logic cs_stbl;
logic fg_count;

logic [$clog2(NUM_CYCLES)-1:0] ff_count;

assign cs_stbl = ~(ff_a ^ ff_b);

always_ff @( posedge clk ) begin
    ff_a <= btn;
    ff_b <= ff_a;
end



always_ff @(posedge clk) begin

    if (cs_stbl) begin

        if (!fg_count)
            ff_count <= ff_count + 1'b1;

    end
    else begin

        ff_count <= '0;

    end

end

assign fg_count = (ff_count == NUM_CYCLES-1)? 1: 0;

always_ff @( posedge clk ) begin
    if (fg_count) begin
        ff_c <= ff_b;
    end
end

assign cs_antreb = ff_c;

endmodule

Proyecto2/src/sim/B2_antreb_tb.sv
`timescale 1ns/1ps

module B2_antreb_tb;

    // =====================================
    // SEÑALES
    // =====================================
    logic clk;
    logic btn;

    logic cs_antreb;

    // =====================================
    // DUT
    // =====================================
    B2_antreb #(
        .NUM_CYCLES(7)
    ) dut (
        .clk(clk),
        .btn(btn),
        .cs_antreb(cs_antreb)
    );

    // =====================================
    // CLOCK
    // =====================================
    initial begin
        clk = 0;
        forever #5 clk = ~clk;
    end

    // =====================================
    // VCD
    // =====================================
    initial begin
        $dumpfile("B2_antreb_tb.vcd");
        $dumpvars(0, B2_antreb_tb);
    end

    // =====================================
    // ESTÍMULOS
    // =====================================
    initial begin

        // estado inicial
        btn = 0;

        #40;

        // =================================
        // REBOTE DE SUBIDA
        // =================================
        btn = 1; #10;
        btn = 0; #10;
        btn = 1; #10;
        btn = 0; #10;
        btn = 1;

        // mantener estable
        #100;

        // =================================
        // REBOTE DE BAJADA
        // =================================
        btn = 0; #10;
        btn = 1; #10;
        btn = 0; #10;
        btn = 1; #10;
        btn = 0;

        // mantener estable
        #100;

        $finish;

    end

endmodule

Proyecto2/src/build/B2_antreb_tb.vcd
$date
	Thu May 14 00:40:22 2026
$end
$version
	Icarus Verilog
$end
$timescale
	1ps
$end
$scope module B2_antreb_tb $end
$var wire 1 ! cs_antreb $end
$var reg 1 " btn $end
$var reg 1 # clk $end
$scope module dut $end
$var wire 1 " btn $end
$var wire 1 # clk $end
$var wire 1 ! cs_antreb $end
$var wire 1 $ cs_stbl $end
$var wire 1 % fg_count $end
$var parameter 32 & NUM_CYCLES $end
$var reg 1 ' ff_a $end
$var reg 1 ( ff_b $end
$var reg 1 ) ff_c $end
$var reg 3 * ff_count [2:0] $end
$upscope $end
$upscope $end
$enddefinitions $end
$comment Show the parameter values. $end
$dumpall
b111 &
$end
#0
$dumpvars
bx *
x)
x(
x'
x%
x$
0#
0"
x!
$end
#5000
0%
0'
b0 *
0!
0)
1#
#10000
0#
#15000
1$
0(
1#
#20000
0#
#25000
b1 *
1#
#30000
0#
#35000
b10 *
1#
#40000
0#
1"
#45000
0$
1'
b11 *
1#
#50000
0#
0"
#55000
b0 *
1(
0'
1#
#60000
0#
1"
#65000
0(
1'
1#
#70000
0#
0"
#75000
1(
0'
1#
#80000
0#
1"
#85000
0(
1'
1#
#90000
0#
#95000
1$
1(
1#
#100000
0#
#105000
b1 *
1#
#110000
0#
#115000
b10 *
1#
#120000
0#
#125000
b11 *
1#
#130000
0#
#135000
b100 *
1#
#140000
0#
#145000
b101 *
1#
#150000
0#
#155000
1%
b110 *
1#
#160000
0#
#165000
0%
b111 *
1!
1)
1#
#170000
0#
#175000
0!
0)
b0 *
1#
#180000
0#
0"
#185000
0$
0'
b1 *
1#
#190000
0#
1"
#195000
b0 *
0(
1'
1#
#200000
0#
0"
#205000
1(
0'
1#
#210000
0#
1"
#215000
0(
1'
1#
#220000
0#
0"
#225000
1(
0'
1#
#230000
0#
#235000
1$
0(
1#
#240000
0#
#245000
b1 *
1#
#250000
0#
#255000
b10 *
1#
#260000
0#
#265000
b11 *
1#
#270000
0#
#275000
b100 *
1#
#280000
0#
#285000
b101 *
1#
#290000
0#
#295000
1%
b110 *
1#
#300000
0#
#305000
0%
b111 *
1#
#310000
0#
#315000
b0 *
1#
