Proyecto2/src/design/bin2bcd.sv
module bin2bcd (
    input  logic [11:0] bin,

    output logic [3:0] miles,
    output logic [3:0] centenas,
    output logic [3:0] decenas,
    output logic [3:0] unidades
);

    integer i;

    logic [11:0] shift_in;
    logic [3:0] b3, b2, b1, b0;

    always_comb begin

        shift_in = bin;

        b3 = 0;
        b2 = 0;
        b1 = 0;
        b0 = 0;

        for (i = 0; i < 12; i = i + 1) begin

            // ===== ajuste BCD manual =====
            if (b3 >= 5) b3 = b3 + 3;
            if (b2 >= 5) b2 = b2 + 3;
            if (b1 >= 5) b1 = b1 + 3;
            if (b0 >= 5) b0 = b0 + 3;

            // shift global
            {b3, b2, b1, b0, shift_in} =
            {b3, b2, b1, b0, shift_in} << 1;

        end

        miles     = b3;
        centenas  = b2;
        decenas   = b1;
        unidades  = b0;

    end

endmodule

Proyecto2/src/sim/bin2bcd_tb.sv
`timescale 1ns/1ps

module bin2bcd_tb;

    // DUT inputs
    logic [11:0] bin;

    // DUT outputs
    logic [3:0] miles;
    logic [3:0] centenas;
    logic [3:0] decenas;
    logic [3:0] unidades;

    // =========================
    // Instancia del DUT
    // =========================
    bin2bcd dut (
        .bin(bin),
        .miles(miles),
        .centenas(centenas),
        .decenas(decenas),
        .unidades(unidades)
    );

    // =========================
    // Task de prueba
    // =========================
    task probar(input [11:0] valor);

        begin

            bin = valor;

            #1;

            $display("-----------------------------------");
            $display("BINARIO = %0d", valor);
            $display("BCD     = %0d%0d%0d%0d",
                     miles,
                     centenas,
                     decenas,
                     unidades);

        end

    endtask

    // =========================
    // Estímulos
    // =========================
    initial begin

        $display("INICIO TEST BIN2BCD");

        probar(0);
        probar(1);
        probar(5);
        probar(9);

        probar(10);
        probar(15);
        probar(42);
        probar(99);

        probar(100);
        probar(255);
        probar(512);

        probar(999);
        probar(1023);

        probar(2048);
        probar(4095);

        $display("FIN TEST");

        $finish;

    end

    initial begin
        $dumpfile("bin2bcd_tb.vcd");
        $dumpvars(0, bin2bcd_tb);
    end

endmodule

Proyecto2/src/build/bin2bcd_tb.vcd
$date
	Wed May 13 13:37:35 2026
$end
$version
	Icarus Verilog
$end
$timescale
	1ps
$end
$scope module bin2bcd_tb $end
$var wire 4 ! unidades [3:0] $end
$var wire 4 " miles [3:0] $end
$var wire 4 # decenas [3:0] $end
$var wire 4 $ centenas [3:0] $end
$var reg 12 % bin [11:0] $end
$scope module dut $end
$var wire 12 & bin [11:0] $end
$var reg 4 ' b0 [3:0] $end
$var reg 4 ( b1 [3:0] $end
$var reg 4 ) b2 [3:0] $end
$var reg 4 * b3 [3:0] $end
$var reg 4 + centenas [3:0] $end
$var reg 4 , decenas [3:0] $end
$var reg 4 - miles [3:0] $end
$var reg 12 . shift_in [11:0] $end
$var reg 4 / unidades [3:0] $end
$var integer 32 0 i [31:0] $end
$upscope $end
$scope task probar $end
$var reg 12 1 valor [11:0] $end
$upscope $end
$upscope $end
$enddefinitions $end
$comment Show the parameter values. $end
$dumpall
$end
#0
$dumpvars
b0 1
b1100 0
b0 /
b0 .
b0 -
b0 ,
b0 +
b0 *
b0 )
b0 (
b0 '
b0 &
b0 %
b0 $
b0 #
b0 "
b0 !
$end
#1000
b1 !
b1 /
b1 '
b1100 0
b0 .
b1 %
b1 &
b1 1
#2000
b101 !
b101 /
b1100 0
b101 '
b0 .
b101 %
b101 &
b101 1
#3000
b1001 !
b1001 /
b1100 0
b1001 '
b0 .
b1001 %
b1001 &
b1001 1
#4000
b0 !
b0 /
b1 #
b1 ,
b1 (
b1100 0
b0 '
b0 .
b1010 %
b1010 &
b1010 1
#5000
b101 !
b101 /
b101 '
b1100 0
b1 (
b0 .
b1111 %
b1111 &
b1111 1
#6000
b10 !
b10 /
b100 #
b100 ,
b1100 0
b10 '
b100 (
b0 .
b101010 %
b101010 &
b101010 1
#7000
b1001 !
b1001 /
b1001 #
b1001 ,
b1100 0
b1001 '
b1001 (
b0 .
b1100011 %
b1100011 &
b1100011 1
#8000
b0 !
b0 /
b0 #
b0 ,
b1 $
b1 +
b1 )
b1100 0
b0 '
b0 (
b0 .
b1100100 %
b1100100 &
b1100100 1
#9000
b101 !
b101 /
b101 #
b101 ,
b10 $
b10 +
b101 (
b101 '
b1100 0
b10 )
b0 .
b11111111 %
b11111111 &
b11111111 1
#10000
b10 !
b10 /
b1 #
b1 ,
b101 $
b101 +
b1100 0
b10 '
b1 (
b101 )
b0 .
b1000000000 %
b1000000000 &
b1000000000 1
#11000
b1001 !
b1001 /
b1001 #
b1001 ,
b1001 $
b1001 +
b1100 0
b1001 '
b1001 (
b1001 )
b0 .
b1111100111 %
b1111100111 &
b1111100111 1
#12000
b11 !
b11 /
b10 #
b10 ,
b0 $
b0 +
b1 "
b1 -
b1 *
b1100 0
b11 '
b10 (
b0 )
b0 .
b1111111111 %
b1111111111 &
b1111111111 1
#13000
b1000 !
b1000 /
b100 #
b100 ,
b10 "
b10 -
b0 )
b1100 0
b1000 '
b100 (
b10 *
b0 .
b100000000000 %
b100000000000 &
b100000000000 1
#14000
b101 !
b101 /
b1001 #
b1001 ,
b100 "
b100 -
b0 )
b1100 0
b101 '
b1001 (
b100 *
b0 .
b111111111111 %
b111111111111 &
b111111111111 1
